{"name":"Ubuntu","_id":"cm6wdppf00005ejqa3bf49a8m","slug":"Ubuntu","path":"tags/Ubuntu/","permalink":"https://blog.leonhardt.tech/tags/Ubuntu/","posts":[{"title":"解决 Ubuntu sshd_config 修改端口无效的问题","date":"2025-02-08T15:57:22.288Z","slug":"解决 Ubuntu sshd_config 修改端口无效的问题","published":true,"updated":"2025-02-08T15:57:22.288Z","_id":"cm6wdppes0001ejqaewjt0bbn","layout":"post","photos":[],"excerpt":"","path":"20250208-解决 Ubuntu sshd_config 修改端口无效的问题/","permalink":"https://blog.leonhardt.tech/20250208-%E8%A7%A3%E5%86%B3%20Ubuntu%20sshd_config%20%E4%BF%AE%E6%94%B9%E7%AB%AF%E5%8F%A3%E6%97%A0%E6%95%88%E7%9A%84%E9%97%AE%E9%A2%98/","__post":true}],"length":1}